LICENSE
MANIFEST.in
README.rst
lazyasd-py2.py
lazyasd-py3.py
lazyasd.py
setup.py
lazyasd.egg-info/PKG-INFO
lazyasd.egg-info/SOURCES.txt
lazyasd.egg-info/dependency_links.txt
lazyasd.egg-info/not-zip-safe
lazyasd.egg-info/top_level.txt