Metadata-Version: 1.1
Name: lazyasd
Version: 0.1.4
Summary: Lazy & self-destructive tools for speeding up module imports
Home-page: https://github.com/xonsh/lazyasd
Author: The xonsh developers
Author-email: xonsh@googlegroups.com
License: BSD 3-clause
Download-URL: https://github.com/xonsh/lazyasd/zipball/0.1.4
Platform: UNKNOWN
Classifier: License :: OSI Approved
Classifier: Intended Audience :: Developers
Classifier: Programming Language :: Python
Classifier: Topic :: Utilities
